r_todolist/__init__.py
r_todolist/main.py
r_todolist-0.1.1.dist-info/entry_points.txt
r_todolist-0.1.1.dist-info/WHEEL
r_todolist-0.1.1.dist-info/METADATA
r_todolist-0.1.1.dist-info/RECORD
