Metadata-Version: 2.1
Name: r-todolist
Version: 0.1.1
Summary: 
Author: reiichii
Author-email: 20413226+reiichii@users.noreply.github.com
Requires-Python: >=3.10,<4.0
Classifier: Programming Language :: Python :: 3
Classifier: Programming Language :: Python :: 3.10
Requires-Dist: typer[all] (>=0.6.1,<0.7.0)
